lol_serializer.cpython-37m-x86_64-linux-gnu.so
lol_serializer-0.0.7.dist-info/METADATA
lol_serializer-0.0.7.dist-info/WHEEL
lol_serializer-0.0.7.dist-info/RECORD
lol_serializer-0.0.7.dist-info/top_level.txt
