Metadata-Version: 2.1
Name: lol-serializer
Version: 0.0.7
Summary: Lol timeline binary serializer
Home-page: https://my.web.site/some_page
Author: Jakub Klimek
Author-email: isl.kuba@gmail.com
